CHANGES.txt
LICENSE.txt
MANIFEST.in
README.rst
cpool.py
setup.py
cpool.egg-info/PKG-INFO
cpool.egg-info/SOURCES.txt
cpool.egg-info/dependency_links.txt
cpool.egg-info/top_level.txt