Metadata-Version: 1.0
Name: cpool
Version: 0.2.2
Summary: Simple Connection Pool handler
Home-page: https://github.com/ex-nerd/cpool
Author: Chris Petersen
Author-email: geek@ex-nerd.com
License: LICENSE.txt
Platform: UNKNOWN
